odoo8_addon_stock_available_unreserved-8.0.1.0.0-py2.7-nspkg.pth
odoo8_addon_stock_available_unreserved-8.0.1.0.0.dist-info/top_level.txt
odoo8_addon_stock_available_unreserved-8.0.1.0.0.dist-info/WHEEL
odoo8_addon_stock_available_unreserved-8.0.1.0.0.dist-info/RECORD
odoo8_addon_stock_available_unreserved-8.0.1.0.0.dist-info/metadata.json
odoo8_addon_stock_available_unreserved-8.0.1.0.0.dist-info/DESCRIPTION.rst
odoo8_addon_stock_available_unreserved-8.0.1.0.0.dist-info/METADATA
odoo8_addon_stock_available_unreserved-8.0.1.0.0.dist-info/namespace_packages.txt
odoo_addons/stock_available_unreserved/__openerp__.py
odoo_addons/stock_available_unreserved/__init__.py
odoo_addons/stock_available_unreserved/README.rst
odoo_addons/stock_available_unreserved/models/product.py
odoo_addons/stock_available_unreserved/models/__init__.py
odoo_addons/stock_available_unreserved/views/stock_quant_view.xml
odoo_addons/stock_available_unreserved/views/product_view.xml
odoo_addons/stock_available_unreserved/tests/test_stock_available_unreserved.py
odoo_addons/stock_available_unreserved/tests/__init__.py
